{
    "salehistory": [
        {
            "amount": 5,
            "name": "牙膏",
            "sales": 80,
            "time": "周四 8月 6 23:32:05 2020"
        },
        {
            "amount": 2,
            "name": "牙膏",
            "sales": 32,
            "time": "周四 8月 6 23:32:05 2020"
        },
        {
            "amount": 1,
            "name": "毛巾",
            "sales": 17.5,
            "time": "周四 8月 6 23:32:05 2020"
        },
        {
            "amount": 1,
            "name": "毛巾",
            "sales": 17.5,
            "time": "周四 8月 6 23:32:05 2020"
        },
        {
            "amount": 2,
            "name": "毛巾",
            "sales": 37.5,
            "time": "周四 8月 6 23:32:05 2020"
        },
        {
            "amount": 5,
            "name": "牙膏",
            "sales": 62.5,
            "time": "周四 8月 6 23:32:05 2020"
        },
        {
            "amount": 3,
            "name": "毛巾",
            "sales": 45,
            "time": "周四 8月 6 23:32:05 2020"
        },
        {
            "amount": 1,
            "name": "牙膏",
            "sales": 20,
            "time": "周四 8月 6 23:32:05 2020"
        },
        {
            "amount": 6,
            "name": "牙膏",
            "sales": 96,
            "time": "周四 8月 6 23:32:05 2020"
        },
        {
            "amount": 1,
            "name": "牙膏",
            "sales": 13,
            "time": "周四 8月 6 23:32:05 2020"
        },
        {
            "amount": 1,
            "name": "毛巾",
            "sales": 15,
            "time": "周四 8月 6 23:32:05 2020"
        },
        {
            "amount": 1,
            "name": "毛巾",
            "sales": 18.75,
            "time": "周四 8月 6 23:32:05 2020"
        },
        {
            "amount": 2,
            "name": "牙膏",
            "sales": 32.5,
            "time": "周四 8月 6 23:32:05 2020"
        },
        {
            "amount": 1,
            "name": "牙膏",
            "sales": 16,
            "time": "周四 8月 6 23:32:05 2020"
        }
    ]
}
